<?xml version="1.0" encoding="utf-8" ?><dwsync><file name="image_02.jpg" server="promociones.liverpool.com.mx//home/oracle/oas/liverpool/" local="3644328954" remote="3644337540" Dst="-1" /><file name="image_03.jpg" server="promociones.liverpool.com.mx//home/oracle/oas/liverpool/" local="3644328824" remote="3644337540" Dst="-1" /><file name="image_01.jpg" server="promociones.liverpool.com.mx//home/oracle/oas/liverpool/" local="3644328896" remote="3644337540" Dst="-1" /><file name="index.html" server="promociones.liverpool.com.mx//home/oracle/oas/liverpool/" local="3642452044" remote="3644337540" Dst="-1" /><file name="image_04.jpg" server="promociones.liverpool.com.mx//home/oracle/oas/liverpool/" local="3644329059" remote="3644337540" Dst="-1" /><file name="image_05.jpg" server="promociones.liverpool.com.mx//home/oracle/oas/liverpool/" local="3644340663" remote="3644340900" Dst="-1" /><file name="logo.jpg" server="promociones.liverpool.com.mx//home/oracle/oas/liverpool/" local="3642452044" remote="3644337540" Dst="-1" /><file name=".DS_Store" server="promociones.liverpool.com.mx//home/oracle/oas/liverpool/" local="3644329023" remote="3644337540" Dst="-1" /></dwsync>